olora/__init__.py
olora/database.py
olora/define.py
olora/packet.py
pyolora-1.1.0.dist-info/METADATA
pyolora-1.1.0.dist-info/WHEEL
pyolora-1.1.0.dist-info/top_level.txt
pyolora-1.1.0.dist-info/RECORD
