Metadata-Version: 2.1
Name: pyolora
Version: 1.1.0
Summary: python wrapper for olorapkt
Home-page: https://github.com/Gibartes/O-LoRa
Author: gibartes
License: UNKNOWN
Download-URL: https://github.com/Gibartes/O-LoRa/tree/master/Device/bluetooth/python/
Platform: UNKNOWN
Classifier: Programming Language :: Python :: 3
Classifier: Programming Language :: Python :: 3.2
Classifier: Programming Language :: Python :: 3.3
Classifier: Programming Language :: Python :: 3.4
Classifier: Programming Language :: Python :: 3.5
Classifier: Programming Language :: Python :: 3.6
Classifier: Programming Language :: Python :: 3.7
Requires-Python: >=3
